Metadata-Version: 1.1
Name: mycroftapi
Version: 2.0
Summary: a library to communicate with Mycroft API
Home-page: https://github.com/Geeked-Out-Solutions/mycroft_api.git
Author: Brian Hopkins
Author-email: UNKNOWN
License: UNKNOWN
Platform: UNKNOWN
Classifier: Development Status :: 3 - Alpha
Classifier: Environment :: Other Environment
Classifier: Intended Audience :: Developers
Classifier: Operating System :: OS Independent
Classifier: Programming Language :: Python
Classifier: Topic :: Home Automation
Classifier: Topic :: Software Development :: Libraries :: Python Modules
